fractional_indexing.py
fractional_indexing-0.1.3.dist-info/LICENCE
fractional_indexing-0.1.3.dist-info/METADATA
fractional_indexing-0.1.3.dist-info/WHEEL
fractional_indexing-0.1.3.dist-info/top_level.txt
fractional_indexing-0.1.3.dist-info/RECORD
