Metadata-Version: 2.1
Name: fractional-indexing
Version: 0.1.3
Summary: Provides functions for generating ordering strings
Home-page: https://github.com/httpie/fractional-indexing-python
License: CC0 1.0 Universal
Project-URL: GitHub, https://github.com/httpie/fractional-indexing-python
Project-URL: Twitter, https://twitter.com/httpie
Project-URL: Discord, https://httpie.io/discord
License-File: LICENCE
Requires-Dist: setuptools
